prefab/__init__.py
prefab/__main__.py
prefab/compare.py
prefab/device.py
prefab/geometry.py
prefab/predict.py
prefab/py.typed
prefab/read.py
prefab/shapes.py
prefab/models/__init__.py
prefab/models/base.py
prefab/models/evaluation.py
prefab-1.5.0.dist-info/METADATA
prefab-1.5.0.dist-info/WHEEL
prefab-1.5.0.dist-info/entry_points.txt
prefab-1.5.0.dist-info/licenses/LICENSE
prefab-1.5.0.dist-info/RECORD
