Metadata-Version: 2.4
Name: prefab
Version: 1.5.0
Summary: Artificial nanofabrication of integrated photonic circuits using deep learning
Project-URL: Homepage, https://prefabphotonics.com
Project-URL: Repository, https://github.com/PreFab-Photonics/PreFab
Project-URL: Docs, https://docs.prefabphotonics.com
Author-email: "PreFab Photonics Inc." <hi@prefabphotonics.com>
License:                   GNU LESSER GENERAL PUBLIC LICENSE
License-File: LICENSE
Keywords: electronic-design-automation,integrated-photonics,inverse-design,lithography,nanofabrication,photonics,semiconductor-manufacturing,silicon-photonics
Classifier: License :: OSI Approved :: GNU Lesser General Public License v2 (LGPLv2)
Classifier: Operating System :: OS Independent
Classifier: Programming Language :: Python :: 3
Requires-Python: >=3.9
Requires-Dist: autograd
Requires-Dist: gdstk>=0.9.55
Requires-Dist: matplotlib
Requires-Dist: numpy
Requires-Dist: opencv-python-headless
Requires-Dist: pillow
Requires-Dist: pydantic>=2.10
Requires-Dist: requests
Requires-Dist: scikit-image
Requires-Dist: scipy
Requires-Dist: toml
Provides-Extra: docs
Requires-Dist: mkdocs; extra == 'docs'
Requires-Dist: mkdocs-material; extra == 'docs'
Requires-Dist: mkdocstrings[python]; extra == 'docs'
